.hgignore
.hgtags
HISTORY.rst
README.rst
TODO.txt
drone.sh
mercurial_extension_utils.py
mercurial_extension_utils_loader.py
noxfile.py
setup.py
mercurial_extension_utils.egg-info/PKG-INFO
mercurial_extension_utils.egg-info/SOURCES.txt
mercurial_extension_utils.egg-info/dependency_links.txt
mercurial_extension_utils.egg-info/top_level.txt
mercurial_extension_utils.egg-info/zip-safe
tests/manual_find_repositories_below.py
tests/py2_doctests_mercurial_extension_utils.py
tests/py2win_doctests_mercurial_extension_utils.py
tests/test_doctest.py
tests/test_find_repositories_below.py
tests/experiments/fixup_spoofout.py