Metadata-Version: 2.1
Name: mercurial_extension_utils
Version: 1.5.3
Summary: Mercurial Extension Utils
Home-page: https://foss.heptapod.net/mercurial/mercurial-extension_utils
Author: Marcin Kasperski
Author-email: Marcin.Kasperski@mekk.waw.pl
License: BSD
Keywords: mercurial hg extension
Classifier: Development Status :: 4 - Beta
Classifier: Environment :: Console
Classifier: Intended Audience :: Developers
Classifier: License :: DFSG approved
Classifier: License :: OSI Approved :: BSD License
Classifier: Programming Language :: Python :: 2
Classifier: Programming Language :: Python :: 3
Classifier: Operating System :: OS Independent
Classifier: Topic :: Software Development :: Libraries :: Python Modules
Classifier: Topic :: Software Development :: Version Control
